TestLibrary/MyLib.py
TestLibrary/__init__.py
TestLibraryOsa-0.0.1.dist-info/METADATA
TestLibraryOsa-0.0.1.dist-info/WHEEL
TestLibraryOsa-0.0.1.dist-info/top_level.txt
TestLibraryOsa-0.0.1.dist-info/RECORD
